dyndbmutex/__init__.py
dyndbmutex/dyndbmutex.py
dyndbmutex-0.4.1.dist-info/LICENSE
dyndbmutex-0.4.1.dist-info/METADATA
dyndbmutex-0.4.1.dist-info/WHEEL
dyndbmutex-0.4.1.dist-info/top_level.txt
dyndbmutex-0.4.1.dist-info/RECORD
